wandb_preempt/__init__.py
wandb_preempt/checkpointer.py
wandb_preempt-0.1.0.dist-info/LICENSE
wandb_preempt-0.1.0.dist-info/METADATA
wandb_preempt-0.1.0.dist-info/WHEEL
wandb_preempt-0.1.0.dist-info/top_level.txt
wandb_preempt-0.1.0.dist-info/RECORD
